<dataStore>
  <id>DataStoreInfoImpl-283893cb:15f0be6b5ce:-7fff</id>
  <name>impiantoRifiuti</name>
  <type>Application Schema DataAccess</type>
  <enabled>true</enabled>
  <workspace>
    <id>WorkspaceInfoImpl-48f89f06:15da81d661f:-7fc7</id>
  </workspace>
  <connectionParameters>
    <entry key="dbtype">app-schema</entry>
    <entry key="url">file:/appserv/tomcat60/data_dir/data/decsiraogc_rifiuti/impiantoRifiuti/impiantoRifiuti.appschema</entry>
    <entry key="namespace">http://www.regione.piemonte.it/ambiente/decsiraogc_rifiuti/1.0</entry>
  </connectionParameters>
  <__default>false</__default>
</dataStore>