<?xml version="1.0" encoding="UTF-8" standalone="yes"?>
<ns3:AppSchemaDataAccess xmlns:ns2="http://www.opengis.net/ogc" xmlns:ns3="http://www.geotools.org/app-schema">
    <namespaces>
        <Namespace>
            <prefix>decsiraogc_idf_ads</prefix>
            <uri>http://www.regione.piemonte.it/ambiente/decsiraogc_idf_ads/1.0</uri>
        </Namespace>
        <Namespace>
            <prefix>gml</prefix>
            <uri>http://www.opengis.net/gml/3.2</uri>
        </Namespace>
    </namespaces>
    <includedTypes/>
    <sourceDataStores>
        <DataStore>
            <id>dataStore</id>
            <parameters>
                <Parameter>
                    <name>Connection timeout</name>
                    <value>20</value>
                </Parameter>
                <Parameter>
                    <name>port</name>
                    <value>${db.port}</value>
                </Parameter>
                <Parameter>
                    <name>passwd</name>
                    <value>${db.password}</value>
                </Parameter>
                <Parameter>
                    <name>dbtype</name>
                    <value>postgis</value>
                </Parameter>
                <Parameter>
                    <name>encode functions</name>
                    <value>true</value>
                </Parameter>
                <Parameter>
                    <name>Evictor run periodicity</name>
                    <value>300</value>
                </Parameter>
                <Parameter>
                    <name>namespace</name>
                    <value></value>
                </Parameter>
                <Parameter>
                    <name>schema</name>
                    <value>${db.schema}</value>
                </Parameter>
                <Parameter>
                    <name>create database</name>
                    <value>false</value>
                </Parameter>
                <Parameter>
                    <name>fetch size</name>
                    <value>1000</value>
                </Parameter>
                <Parameter>
                    <name>preparedStatements</name>
                    <value>false</value>
                </Parameter>
                <Parameter>
                    <name>min connections</name>
                    <value>1</value>
                </Parameter>
                <Parameter>
                    <name>Evictor tests per run</name>
                    <value>3</value>
                </Parameter>
                <Parameter>
                    <name>host</name>
                    <value>${db.host}</value>
                </Parameter>
                <Parameter>
                    <name>validate connections</name>
                    <value>true</value>
                </Parameter>
                <Parameter>
                    <name>max connections</name>
                    <value>10</value>
                </Parameter>
                <Parameter>
                    <name>database</name>
                    <value>${db.name}</value>
                </Parameter>
                <Parameter>
                    <name>Support on the fly geometry simplification</name>
                    <value>true</value>
                </Parameter>
                <Parameter>
                    <name>Max connection idle time</name>
                    <value>300</value>
                </Parameter>
                <Parameter>
                    <name>Test while idle</name>
                    <value>true</value>
                </Parameter>
                <Parameter>
                    <name>Loose bbox</name>
                    <value>true</value>
                </Parameter>
                <Parameter>
                    <name>Expose primary keys</name>
                    <value>true</value>
                </Parameter>
                <Parameter>
                    <name>Max open prepared statements</name>
                    <value>50</value>
                </Parameter>
                <Parameter>
                    <name>Estimated extends</name>
                    <value>true</value>
                </Parameter>
                <Parameter>
                    <name>user</name>
                    <value>${db.user}</value>
                </Parameter>
            </parameters>
        </DataStore>
    </sourceDataStores>
    <targetTypes>
        <FeatureType>
            <schemaUri>_schemas/areaDiSaggio.xsd</schemaUri>
        </FeatureType>
    </targetTypes>
    <typeMappings>
        <FeatureTypeMapping>
            <sourceDataStore>dataStore</sourceDataStore>
            <sourceType>decsira_t_idf_specie_alberi</sourceType>
            <targetElement>decsiraogc_idf_ads:SpecieAlberi</targetElement>
            <attributeMappings>
                <AttributeMapping>
                    <targetAttribute>decsiraogc_idf_ads:idSpecieAlberi </targetAttribute>
                    <sourceExpression>
                        <OCQL>id_specie_alberi</OCQL>
                    </sourceExpression>
                </AttributeMapping>
                <AttributeMapping>
                    <targetAttribute>decsiraogc_idf_ads:SpecieAlberi</targetAttribute>
                    <idExpression>
                        <OCQL>strConcat('id_specie_alberi.', id_specie_alberi)</OCQL>
                    </idExpression>
                </AttributeMapping>
                <AttributeMapping>
                    <targetAttribute>decsiraogc_idf_ads:altezza</targetAttribute>
                    <sourceExpression>
                        <OCQL>altezza</OCQL>
                    </sourceExpression>
                </AttributeMapping>
                <AttributeMapping>
                    <targetAttribute>decsiraogc_idf_ads:codGruppo</targetAttribute>
                    <sourceExpression>
                        <OCQL>cod_gruppo</OCQL>
                    </sourceExpression>
                </AttributeMapping>
                <AttributeMapping>
                    <targetAttribute>decsiraogc_idf_ads:codicePignatti</targetAttribute>
                    <sourceExpression>
                        <OCQL>codice_pignatti</OCQL>
                    </sourceExpression>
                </AttributeMapping>
                <AttributeMapping>
                    <targetAttribute>decsiraogc_idf_ads:codiceSpecie</targetAttribute>
                    <sourceExpression>
                        <OCQL>codice_specie</OCQL>
                    </sourceExpression>
                </AttributeMapping>
                <AttributeMapping>
                    <targetAttribute>decsiraogc_idf_ads:codTipoCampioneDom</targetAttribute>
                    <sourceExpression>
                        <OCQL>cod_tipo_campione</OCQL>
                    </sourceExpression>
                </AttributeMapping>
                <AttributeMapping>
                    <targetAttribute>decsiraogc_idf_ads:codTipoCampionePrinc</targetAttribute>
                    <sourceExpression>
                        <OCQL>descr_tipo_campione</OCQL>
                    </sourceExpression>
                </AttributeMapping>
                <AttributeMapping>
                    <targetAttribute>decsiraogc_idf_ads:desTavolaCoeffcub</targetAttribute>
                    <sourceExpression>
                        <OCQL>des_tavola_coeff_cub</OCQL>
                    </sourceExpression>
                </AttributeMapping>
                <AttributeMapping>
                    <targetAttribute>decsiraogc_idf_ads:diametro</targetAttribute>
                    <sourceExpression>
                        <OCQL>diametro</OCQL>
                    </sourceExpression>
                </AttributeMapping>
                <AttributeMapping>
                    <targetAttribute>decsiraogc_idf_ads:eta</targetAttribute>
                    <sourceExpression>
                        <OCQL>eta</OCQL>
                    </sourceExpression>
                </AttributeMapping>
                <AttributeMapping>
                    <targetAttribute>decsiraogc_idf_ads:fkConfigIpla</targetAttribute>
                    <sourceExpression>
                        <OCQL>fk_config_ipla</OCQL>
                    </sourceExpression>
                </AttributeMapping>
                <AttributeMapping>
                    <targetAttribute>decsiraogc_idf_ads:fkTipoAds</targetAttribute>
                    <sourceExpression>
                        <OCQL>fk_tipo_ads</OCQL>
                    </sourceExpression>
                </AttributeMapping>
                <AttributeMapping>
                    <targetAttribute>decsiraogc_idf_ads:flgConiflatif</targetAttribute>
                    <sourceExpression>
                        <OCQL>flg_coniflatif</OCQL>
                    </sourceExpression>
                </AttributeMapping>
                <AttributeMapping>
                    <targetAttribute>decsiraogc_idf_ads:idSpecie</targetAttribute>
                    <sourceExpression>
                        <OCQL>id_specie</OCQL>
                    </sourceExpression>
                </AttributeMapping>
                <AttributeMapping>
                    <targetAttribute>decsiraogc_idf_ads:idgeoPtAds</targetAttribute>
                    <sourceExpression>
                        <OCQL>idgeo_pt_ads</OCQL>
                    </sourceExpression>
                </AttributeMapping>
                <AttributeMapping>
                    <targetAttribute>decsiraogc_idf_ads:incremento</targetAttribute>
                    <sourceExpression>
                        <OCQL>incremento</OCQL>
                    </sourceExpression>
                </AttributeMapping>
                <AttributeMapping>
                    <targetAttribute>decsiraogc_idf_ads:note</targetAttribute>
                    <sourceExpression>
                        <OCQL>note</OCQL>
                    </sourceExpression>
                </AttributeMapping>
                <AttributeMapping>
                    <targetAttribute>decsiraogc_idf_ads:nrAlberiPollone</targetAttribute>
                    <sourceExpression>
                        <OCQL>nr_alberi_pollone</OCQL>
                    </sourceExpression>
                </AttributeMapping>
                <AttributeMapping>
                    <targetAttribute>decsiraogc_idf_ads:nrAlberiSeme</targetAttribute>
                    <sourceExpression>
                        <OCQL>nr_alberi_seme</OCQL>
                    </sourceExpression>
                </AttributeMapping>
                <AttributeMapping>
                    <targetAttribute>decsiraogc_idf_ads:numTavolaCoeffCub</targetAttribute>
                    <sourceExpression>
                        <OCQL>num_tavola_coeff_cub</OCQL>
                    </sourceExpression>
                </AttributeMapping>
                <AttributeMapping>
                    <targetAttribute>decsiraogc_idf_ads:specie</targetAttribute>
                    <sourceExpression>
                        <OCQL>specie</OCQL>
                    </sourceExpression>
                </AttributeMapping>
                <AttributeMapping>
                    <targetAttribute>decsiraogc_idf_ads:flgSemePollone</targetAttribute>
                    <sourceExpression>
                        <OCQL>qualita</OCQL>
                    </sourceExpression>
                </AttributeMapping>
                <AttributeMapping>
                    <targetAttribute>decsiraogc_idf_ads:descrTipoAds</targetAttribute>
                    <sourceExpression>
                        <OCQL>tipologia_rilievo</OCQL>
                    </sourceExpression>
                </AttributeMapping>
                <AttributeMapping>
                    <targetAttribute>FEATURE_LINK[1]</targetAttribute>
                    <sourceExpression>
                        <OCQL>idgeo_pt_ads</OCQL>
                    </sourceExpression>
                </AttributeMapping>
            </attributeMappings>
        </FeatureTypeMapping>
    </typeMappings>
</ns3:AppSchemaDataAccess>
